lorem/__init__.py
lorem/data.py
lorem/text.py
lorem-0.1.1.dist-info/DESCRIPTION.rst
lorem-0.1.1.dist-info/METADATA
lorem-0.1.1.dist-info/RECORD
lorem-0.1.1.dist-info/WHEEL
lorem-0.1.1.dist-info/metadata.json
lorem-0.1.1.dist-info/top_level.txt
